camera_discovery/CameraDiscovery.py
camera_discovery/__init__.py
camera_discovery-1.0.11.dist-info/LICENSE.txt
camera_discovery-1.0.11.dist-info/METADATA
camera_discovery-1.0.11.dist-info/WHEEL
camera_discovery-1.0.11.dist-info/top_level.txt
camera_discovery-1.0.11.dist-info/RECORD
