Metadata-Version: 2.1
Name: camera-discovery
Version: 1.0.11
Summary: A package to discover all onvif cameras on your network
Home-page: https://github.com/ricardobf/camera_discovery
Author: Ricardo Barbosa Filho
Author-email: ricardob@dcc.ufmg.br
License: UNKNOWN
Platform: UNKNOWN
Classifier: Natural Language :: English
Classifier: Programming Language :: Python :: 3.6
Classifier: License :: OSI Approved :: MIT License
Classifier: Operating System :: POSIX :: Linux
Requires-Python: >=3.6
Requires-Dist: onvif-zeep (==0.2.12)
Requires-Dist: WSDiscovery (==0.2)
Requires-Dist: netifaces (==0.10.7)
